{
  "servers": {
    "description": "ComfyUI 服务端配置，每行一个。\n格式：id;IP:端口;[token]\nid 为数字标识，0 号固定为默认服务器。token 为可选，用于 ComfyUI-Login 鉴权。\n示例：\n0;127.0.0.1:8188\n1;192.168.1.200:8188;my_token_here",
    "type": "text",
    "default": "0;127.0.0.1:8188"
  },
  "workflows": {
    "description": "ComfyUI 工作流配置，每行一个。\n格式：id;工作流文件;正面节点ID;负面节点ID;输出节点ID;服务器ID\nid 为数字标识，0 号固定为默认工作流。负面节点ID、输出节点ID和服务器ID可留空。服务器ID留空则使用 0 号服务器。\n示例：\n0;workflow_api.json;6;7;;0\n1;workflow_sdxl.json;56;57;9;1",
    "type": "text",
    "default": "0;workflow_api.json;6;7;;0"
  },
  "queue_delay_messages": {
    "description": "队列提示消息，每行一条。{n} 会被替换为待处理任务数。留空使用默认消息。",
    "type": "text",
    "default": "前面还有{n}个稿，别催了\n前面还有{n}个稿，再等等吧\n前面还有{n}个稿，算力就这么点别着急\n前面还有{n}个稿，耐心点小子"
  },
  "drawing_prompt_messages": {
    "description": "首个任务的提示消息，每行一条。留空使用默认消息。",
    "type": "text",
    "default": "在画了在画了，请等一会儿……\n你站在原地不要走动，我给你画一幅\n🎨 在画了，请稍等一会..."
  },
  "control": {
    "description": "访问和安全控制",
    "type": "object",
    "items": {
      "cooldown_seconds": {
        "description": "用户命令冷却时间（秒）",
        "type": "int",
        "default": 35
      },
      "admin_ids": {
        "description": "管理员 QQ 号（列表）",
        "type": "list",
        "default": []
      },
      "whitelist_group_ids": {
        "description": "允许使用的群（白名单）",
        "type": "list",
        "default": []
      },
      "default_group_policy": {
        "description": "白名单群默认敏感词策略 [none/lite/full]",
        "type": "string",
        "default": "lite"
      },
      "default_private_policy": {
        "description": "私聊默认敏感词策略 [none/lite/full]",
        "type": "string",
        "default": "lite"
      },
      "lockdown": {
        "description": "全局锁定 (仅管理员可用)",
        "type": "bool",
        "default": false
      },
      "lockdown_command_enabled": {
        "description": "启用 /comfy_lock 命令开关（管理员可动态开关全局锁定）",
        "type": "bool",
        "default": true
      },
      "admin_bypass": {
        "description": "管理员特权设置",
        "type": "object",
        "items": {
          "whitelist": {
            "description": "管理员无视群聊白名单",
            "type": "bool",
            "default": true
          },
          "cooldown": {
            "description": "管理员无视冷却时间",
            "type": "bool",
            "default": true
          },
          "sensitive_words": {
            "description": "管理员无视敏感词过滤",
            "type": "bool",
            "default": true
          }
        }
      }
    }
  },
  "tagger_model": {
    "description": "WD14 Tagger 模型名称。如果不确定，先在 ComfyUI 节点管理器中确认【WD14Tagger|pysssss】节点的 model 字段可选值。",
    "type": "string",
    "default": "wd-v1-4-moat-tagger-v2"
  }
}
